{
  "$schema": "../node_modules/@tauri-apps/cli/config.schema.json",
  "productName": "EcoSystem Beta",
  "version": "0.1.0",
  "identifier": "com.ecosystem.beta.v2",
  "build": {
    "frontendDist": "../out",
    "devUrl": "http://localhost:3000",
    "beforeDevCommand": "npm run dev",
    "beforeBuildCommand": "npm run build"
  },
  "app": {
    "windows": [
      {
        "title": "EcoSystem Testers Beta v0.1.0",
        "width": 800,
        "height": 600,
        "resizable": true,
        "fullscreen": false
      }
    ],
    "security": {
      "csp": null
    }
  },
  "plugins": {
    "updater": {
      "endpoints": [
        "https://api.github.com/repos/Mindfreaken/ecotesters/releases/latest"
      ],
      "pubkey": "dW50cnVzdGVkIGNvbW1lbnQ6IG1pbmlzaWduIHB1YmxpYyBrZXk6IEZEQTM5NzlENDAxOTk5MTAKUldRUW1SbEFuWmVqL1VYckJUd2hjWlAzTmhyZWg3SlUvUGdZVExtTFNNYU9pUGxYOFlrenR3cEwK"
    }
  },
  "bundle": {
    "active": true,
    "targets": "all",
    "icon": [
      "icons/32x32.png",
      "icons/128x128.png",
      "icons/128x128@2x.png",
      "icons/icon.icns",
      "icons/icon.ico"
    ]
  }
}